{
  "name": "Danny Sharp",
  "age": 49,
  "address": {
    "street": "Aweca Path",
    "city": "Rifollu",
    "state": "CA",
    "zip": "28046"
  },
  "contact": {
    "phone": "(403) 828-6754",
    "servicePhone": "800139899"
  },
  "birthday": "1971-01-20T10:00:44.186Z",
  "ip": "135.39.191.133",
  "foo": "bar",
  "profile": {
    "about": "Teadako kucozo damtupguw mincodli fodjov sieg sanwecoz he muriof vugbon cahukuruk zu zutcuf ucajep. Vesfo fevnimko ruhrihvo livgise siune voboz fok hajipipi kipan gusuc guvezcum udvuz wo itieno zomuznis pu nuazvog ole. Lecuc lapigi vunece def viub iboh rarzuoji nofmip il unizo gi mikgomi raru nebhifoz kapkaw jiwotiili. Rozoh ru wemifcu kukazu muleg jidula ub pi puthor hezusik roh bolat ohu lemav. Iw hocci hu pecgofug rit nog lalpaz fokkereja usfi kownehpog vemkir ecukaphoh un nume.",
    "bio": "Eha cizelapo ojogivvo zemi licni guscahaw lomfow mo hafumi vowimrat gu ito wunli te petatge reg uhateh. Zekpufu cu pibnafde lu mev ligcaib hazosof gut hezkado eh vi fote to jemod gemfigwi zivjo inuce. Vucbuw tahjaive subomo imfa kagfobbor poufato tuv cimnez tisup juwpa rur fes ojwucwih guw datemcik liji warzav mogoj. Ekiuz hes va wu siw nasnige osma befdeh dordab fekor jusjur netwe guoviwo gu."
  },
  "apiKey": "215cf240e74e0fbda84f54b2c08f23574daace29b1de9fc19ecdf9655b7c91c3",
  "currency": {
    "code": "SGD",
    "name": "Singapore Dollar"
  }
}