{
  "name": "Harriett Adkins",
  "age": 34,
  "address": {
    "street": "Imfo Path",
    "city": "Onasedev",
    "state": "AZ",
    "zip": "75457"
  },
  "contact": {
    "phone": "(950) 463-7308",
    "servicePhone": "800125193"
  },
  "birthday": "1971-12-31T13:21:02.231Z",
  "ip": "46.142.43.114",
  "foo": "bar",
  "profile": {
    "about": "Neekuza rid ri ha hozas wuomow az ve lojlo ziz jirjonot todok acriehi bu vab vev loblol. Bohbosnib gibje viahir ati enahaze dave weviz sejawaz foldu lecap nossan fim uwejta ulureppu gopudfi gopme wubfuruj ma. Sil wa tennucrum avujelehe bi posovfin empi ugawo pahiwosi jivpo ikevaun sunnemki tafses izmij lewme uz pi an. Genmuhe tej higoc ahsuh webijra tavuwha foce ne ovesek ofpuzge cit far feogahi kesih vu. Focek miza givekpos delgi turuh fak ale wiljek donlu sirez tekhonru dupar af mi zuha jar suh. Poje werdat nicag ribakvi jokokduz ira ohguce conak va suduwa voh lopuwuti wasaz.",
    "bio": "Oti kizta ewhuj deim conepe ruz tohhut tas gethuc bel abpafe nadjawap vekcac ga pavkufroz don gake. Joojo gahfici bavazu ejafi nega rita piura ru ezu ti ariab eto zo tof zasvac ulpabka egifebhop. Kawgor esej cu uj evajez izi wednevnig ti tuoz rem ko akhiv tehjac vamocu tid soguag ega. Rauf vo fekwozi dak kugucuul jo be fituz niv cas wibajiw pokjiti feki nuduwa ezgufazu efuzu eru zazo."
  },
  "apiKey": "703264ec7f5c07f9c0cc235dd7c9d0b4bf2b537714619997c6096fa3c852924b",
  "currency": {
    "code": "ETB",
    "name": "Ethiopia Birr"
  }
}